setup.py
ueli_probability/Binominaldistribution.py
ueli_probability/Gaussiandistribution.py
ueli_probability/Generaldistribution.py
ueli_probability/__init__.py
ueli_probability/test.py
ueli_probability.egg-info/PKG-INFO
ueli_probability.egg-info/SOURCES.txt
ueli_probability.egg-info/dependency_links.txt
ueli_probability.egg-info/not-zip-safe
ueli_probability.egg-info/top_level.txt