Metadata-Version: 1.0
Name: ueli-probability
Version: 0.1
Summary: Gaussian and Binominal distributions
Home-page: UNKNOWN
Author: Eliane Netto
Author-email: elianenetto82@gmail.com
License: UNKNOWN
Platform: UNKNOWN
